[{"x":0,"y":570,"image":"floor.png","scale":"1","_constructor":"jaws.Sprite","alpha":1,"flipped":false,"angle":0,"scale_x":"1","scale_y":"1","anchor_x":0,"anchor_y":0},{"x":30,"y":570,"image":"floor.png","scale":"1","_constructor":"jaws.Sprite","alpha":1,"flipped":false,"angle":0,"scale_x":"1","scale_y":"1","anchor_x":0,"anchor_y":0},{"x":60,"y":570,"image":"floor.png","scale":"1","_constructor":"jaws.Sprite","alpha":1,"flipped":false,"angle":0,"scale_x":"1","scale_y":"1","anchor_x":0,"anchor_y":0},{"x":90,"y":570,"image":"floor.png","scale":"1","_constructor":"jaws.Sprite","alpha":1,"flipped":false,"angle":0,"scale_x":"1","scale_y":"1","anchor_x":0,"anchor_y":0},{"x":120,"y":570,"image":"floor.png","scale":"1","_constructor":"jaws.Sprite","alpha":1,"flipped":false,"angle":0,"scale_x":"1","scale_y":"1","anchor_x":0,"anchor_y":0},{"x":150,"y":570,"image":"floor.png","scale":"1","_constructor":"jaws.Sprite","alpha":1,"flipped":false,"angle":0,"scale_x":"1","scale_y":"1","anchor_x":0,"anchor_y":0},{"x":180,"y":570,"image":"floor.png","scale":"1","_constructor":"jaws.Sprite","alpha":1,"flipped":false,"angle":0,"scale_x":"1","scale_y":"1","anchor_x":0,"anchor_y":0},{"x":210,"y":570,"image":"floor.png","scale":"1","_constructor":"jaws.Sprite","alpha":1,"flipped":false,"angle":0,"scale_x":"1","scale_y":"1","anchor_x":0,"anchor_y":0},{"x":240,"y":570,"image":"floor.png","scale":"1","_constructor":"jaws.Sprite","alpha":1,"flipped":false,"angle":0,"scale_x":"1","scale_y":"1","anchor_x":0,"anchor_y":0},{"x":270,"y":570,"image":"floor.png","scale":"1","_constructor":"jaws.Sprite","alpha":1,"flipped":false,"angle":0,"scale_x":"1","scale_y":"1","anchor_x":0,"anchor_y":0},{"x":300,"y":570,"image":"floor.png","scale":"1","_constructor":"jaws.Sprite","alpha":1,"flipped":false,"angle":0,"scale_x":"1","scale_y":"1","anchor_x":0,"anchor_y":0},{"x":330,"y":570,"image":"floor.png","scale":"1","_constructor":"jaws.Sprite","alpha":1,"flipped":false,"angle":0,"scale_x":"1","scale_y":"1","anchor_x":0,"anchor_y":0},{"x":360,"y":570,"image":"floor.png","scale":"1","_constructor":"jaws.Sprite","alpha":1,"flipped":false,"angle":0,"scale_x":"1","scale_y":"1","anchor_x":0,"anchor_y":0},{"x":390,"y":570,"image":"floor.png","scale":"1","_constructor":"jaws.Sprite","alpha":1,"flipped":false,"angle":0,"scale_x":"1","scale_y":"1","anchor_x":0,"anchor_y":0},{"x":420,"y":570,"image":"floor.png","scale":"1","_constructor":"jaws.Sprite","alpha":1,"flipped":false,"angle":0,"scale_x":"1","scale_y":"1","anchor_x":0,"anchor_y":0},{"x":450,"y":570,"image":"floor.png","scale":"1","_constructor":"jaws.Sprite","alpha":1,"flipped":false,"angle":0,"scale_x":"1","scale_y":"1","anchor_x":0,"anchor_y":0},{"x":480,"y":570,"image":"floor.png","scale":"1","_constructor":"jaws.Sprite","alpha":1,"flipped":false,"angle":0,"scale_x":"1","scale_y":"1","anchor_x":0,"anchor_y":0},{"x":510,"y":570,"image":"floor.png","scale":"1","_constructor":"jaws.Sprite","alpha":1,"flipped":false,"angle":0,"scale_x":"1","scale_y":"1","anchor_x":0,"anchor_y":0},{"x":540,"y":570,"image":"floor.png","scale":"1","_constructor":"jaws.Sprite","alpha":1,"flipped":false,"angle":0,"scale_x":"1","scale_y":"1","anchor_x":0,"anchor_y":0},{"x":570,"y":570,"image":"floor.png","scale":"1","_constructor":"jaws.Sprite","alpha":1,"flipped":false,"angle":0,"scale_x":"1","scale_y":"1","anchor_x":0,"anchor_y":0},{"x":600,"y":570,"image":"floor.png","scale":"1","_constructor":"jaws.Sprite","alpha":1,"flipped":false,"angle":0,"scale_x":"1","scale_y":"1","anchor_x":0,"anchor_y":0},{"x":630,"y":570,"image":"floor.png","scale":"1","_constructor":"jaws.Sprite","alpha":1,"flipped":false,"angle":0,"scale_x":"1","scale_y":"1","anchor_x":0,"anchor_y":0},{"x":660,"y":570,"image":"floor.png","scale":"1","_constructor":"jaws.Sprite","alpha":1,"flipped":false,"angle":0,"scale_x":"1","scale_y":"1","anchor_x":0,"anchor_y":0},{"x":690,"y":570,"image":"floor.png","scale":"1","_constructor":"jaws.Sprite","alpha":1,"flipped":false,"angle":0,"scale_x":"1","scale_y":"1","anchor_x":0,"anchor_y":0},{"x":720,"y":570,"image":"floor.png","scale":"1","_constructor":"jaws.Sprite","alpha":1,"flipped":false,"angle":0,"scale_x":"1","scale_y":"1","anchor_x":0,"anchor_y":0},{"x":750,"y":570,"image":"floor.png","scale":"1","_constructor":"jaws.Sprite","alpha":1,"flipped":false,"angle":0,"scale_x":"1","scale_y":"1","anchor_x":0,"anchor_y":0},{"x":780,"y":570,"image":"floor.png","scale":"1","_constructor":"jaws.Sprite","alpha":1,"flipped":false,"angle":0,"scale_x":"1","scale_y":"1","anchor_x":0,"anchor_y":0},{"x":810,"y":570,"image":"floor.png","scale":"1","_constructor":"jaws.Sprite","alpha":1,"flipped":false,"angle":0,"scale_x":"1","scale_y":"1","anchor_x":0,"anchor_y":0},{"x":840,"y":570,"image":"floor.png","scale":"1","_constructor":"jaws.Sprite","alpha":1,"flipped":false,"angle":0,"scale_x":"1","scale_y":"1","anchor_x":0,"anchor_y":0},{"x":870,"y":570,"image":"floor.png","scale":"1","_constructor":"jaws.Sprite","alpha":1,"flipped":false,"angle":0,"scale_x":"1","scale_y":"1","anchor_x":0,"anchor_y":0},{"x":900,"y":570,"image":"floor.png","scale":"1","_constructor":"jaws.Sprite","alpha":1,"flipped":false,"angle":0,"scale_x":"1","scale_y":"1","anchor_x":0,"anchor_y":0},{"x":930,"y":570,"image":"floor.png","scale":"1","_constructor":"jaws.Sprite","alpha":1,"flipped":false,"angle":0,"scale_x":"1","scale_y":"1","anchor_x":0,"anchor_y":0},{"x":960,"y":570,"image":"floor.png","scale":"1","_constructor":"jaws.Sprite","alpha":1,"flipped":false,"angle":0,"scale_x":"1","scale_y":"1","anchor_x":0,"anchor_y":0},{"x":990,"y":570,"image":"floor.png","scale":"1","_constructor":"jaws.Sprite","alpha":1,"flipped":false,"angle":0,"scale_x":"1","scale_y":"1","anchor_x":0,"anchor_y":0},{"x":1020,"y":570,"image":"floor.png","scale":"1","_constructor":"jaws.Sprite","alpha":1,"flipped":false,"angle":0,"scale_x":"1","scale_y":"1","anchor_x":0,"anchor_y":0},{"x":1050,"y":570,"image":"floor.png","scale":"1","_constructor":"jaws.Sprite","alpha":1,"flipped":false,"angle":0,"scale_x":"1","scale_y":"1","anchor_x":0,"anchor_y":0},{"x":1080,"y":570,"image":"floor.png","scale":"1","_constructor":"jaws.Sprite","alpha":1,"flipped":false,"angle":0,"scale_x":"1","scale_y":"1","anchor_x":0,"anchor_y":0},{"x":1110,"y":570,"image":"floor.png","scale":"1","_constructor":"jaws.Sprite","alpha":1,"flipped":false,"angle":0,"scale_x":"1","scale_y":"1","anchor_x":0,"anchor_y":0},{"x":1140,"y":570,"image":"floor.png","scale":"1","_constructor":"jaws.Sprite","alpha":1,"flipped":false,"angle":0,"scale_x":"1","scale_y":"1","anchor_x":0,"anchor_y":0},{"x":1170,"y":570,"image":"floor.png","scale":"1","_constructor":"jaws.Sprite","alpha":1,"flipped":false,"angle":0,"scale_x":"1","scale_y":"1","anchor_x":0,"anchor_y":0},{"x":1200,"y":570,"image":"floor.png","scale":"1","_constructor":"jaws.Sprite","alpha":1,"flipped":false,"angle":0,"scale_x":"1","scale_y":"1","anchor_x":0,"anchor_y":0},{"x":1230,"y":570,"image":"floor.png","scale":"1","_constructor":"jaws.Sprite","alpha":1,"flipped":false,"angle":0,"scale_x":"1","scale_y":"1","anchor_x":0,"anchor_y":0},{"x":0,"y":0,"image":"switch.png","scale":"1","_constructor":"jaws.Sprite","alpha":1,"flipped":false,"angle":0,"scale_x":"1","scale_y":"1","anchor_x":0,"anchor_y":0},{"x":510,"y":540,"image":"switch.png","scale":"1","_constructor":"jaws.Sprite","alpha":1,"flipped":false,"angle":0,"scale_x":"1","scale_y":"1","anchor_x":0,"anchor_y":0}]